one_chat/__init__.py
one_chat/broadcast_sender.py
one_chat/get_friends_and_groups.py
one_chat/image_carousel_sender.py
one_chat/location_sender.py
one_chat/message_sender.py
one_chat/one_chat.py
one_chat/py.typed
one_chat/quickreply_sender.py
one_chat/sticker_sender.py
one_chat_api-0.4.1.dist-info/licenses/LICENSE
one_chat_api-0.4.1.dist-info/METADATA
one_chat_api-0.4.1.dist-info/WHEEL
one_chat_api-0.4.1.dist-info/top_level.txt
one_chat_api-0.4.1.dist-info/RECORD
