Metadata-Version: 2.4
Name: one-chat-api
Version: 0.4.1
Summary: Python client for OneChat API: messages, files, broadcasts, locations, stickers, templates, quick replies, and image carousel.
Author: Pargorn Ruasijan (xNewz)
Author-email: "Pargorn Ruasijan (xNewz)" <contact@pargorn.com>
License: MIT
Project-URL: Homepage, https://github.com/xnewz/one-chat-api
Project-URL: Repository, https://github.com/xnewz/one-chat-api
Project-URL: Issues, https://github.com/xnewz/one-chat-api/issues
Classifier: Programming Language :: Python :: 3
Classifier: Programming Language :: Python :: 3.8
Classifier: Programming Language :: Python :: 3.9
Classifier: Programming Language :: Python :: 3.10
Classifier: Programming Language :: Python :: 3.11
Classifier: Programming Language :: Python :: 3.12
Classifier: License :: OSI Approved :: MIT License
Classifier: Operating System :: OS Independent
Requires-Python: >=3.8
License-File: LICENSE
Requires-Dist: requests>=2.32.2
Dynamic: author
Dynamic: license-file
Dynamic: requires-python
